heliclockter/__init__.py
heliclockter/py.typed
heliclockter-3.0.1.dist-info/licenses/LICENSE
heliclockter-3.0.1.dist-info/METADATA
heliclockter-3.0.1.dist-info/WHEEL
heliclockter-3.0.1.dist-info/top_level.txt
heliclockter-3.0.1.dist-info/RECORD
