Metadata-Version: 2.4
Name: heliclockter
Version: 3.0.1
Summary: A robust way of dealing with datetimes in python by ensuring all datetimes are timezone aware at runtime.
Author-email: Peter Nilsson <peter.nilsson@channable.com>
License: BSD 3-Clause License
Project-URL: Homepage, https://github.com/channable/heliclockter
Keywords: datetime,heliclockter,timezone,timezones,tz,tzinfo
Classifier: Development Status :: 5 - Production/Stable
Classifier: Intended Audience :: Developers
Classifier: Natural Language :: English
Classifier: Operating System :: Unix
Classifier: Programming Language :: Python :: 3
Classifier: Programming Language :: Python :: 3.10
Classifier: Programming Language :: Python :: 3.11
Classifier: Programming Language :: Python :: 3.12
Classifier: Programming Language :: Python :: 3.13
Classifier: Programming Language :: Python :: 3.14
Classifier: Typing :: Typed
Requires-Python: >=3.10
License-File: LICENSE
Provides-Extra: all
Requires-Dist: bandit; extra == "all"
Requires-Dist: ruff; extra == "all"
Requires-Dist: mypy; extra == "all"
Requires-Dist: pydantic>=2; extra == "all"
Requires-Dist: pylint; extra == "all"
Requires-Dist: pytest; extra == "all"
Requires-Dist: parameterized; extra == "all"
Requires-Dist: toml; extra == "all"
Requires-Dist: tzdata; extra == "all"
Dynamic: license-file
